miplib_benchmark/__init__.py
miplib_benchmark/cli.py
miplib_benchmark/download.py
miplib_benchmark/instance.py
miplib_benchmark/logger.py
miplib_benchmark/metadata.py
miplib_benchmark/path.py
miplib_benchmark/setup.py
miplib_benchmark/solve.py
miplib_benchmark/unzip.py
miplib_benchmark/data/instances.csv
miplib_benchmark-0.1.2.dist-info/METADATA
miplib_benchmark-0.1.2.dist-info/WHEEL
miplib_benchmark-0.1.2.dist-info/entry_points.txt
miplib_benchmark-0.1.2.dist-info/RECORD
