Metadata-Version: 2.3
Name: miplib_benchmark
Version: 0.1.2
Summary: Add your description here
Requires-Python: >=3.12
Requires-Dist: click>=8.1.7
Requires-Dist: highspy>=1.8.1
Requires-Dist: polars>=1.15.0
Requires-Dist: requests>=2.32.3
Requires-Dist: tqdm>=4.67.1
